CHANGELOG.txt
LICENCE.txt
MANIFEST.in
README.txt
requirement.txt
setup.py
rfmlp/__init__.py
rfmlp.egg-info/PKG-INFO
rfmlp.egg-info/SOURCES.txt
rfmlp.egg-info/dependency_links.txt
rfmlp.egg-info/top_level.txt