Metadata-Version: 1.1
Name: rfmlp
Version: 0.0.1
Summary: Ritesh fantastic ML Package
Home-page: UNKNOWN
Author: Ritesh Yadav
Author-email: daydreamingguy941@gmail.com
License: MIT
Keywords: Machine Learning,Datasets
Platform: UNKNOWN
Classifier: Development Status :: 5 - Production/Stable
Classifier: Intended Audience :: Education
Classifier: Operating System :: Microsoft :: Windows :: Windows 10
Classifier: License :: OSI Approved :: MIT License
Classifier: Programming Language :: Python :: 3
